setup.py
spouk_utils/__init__.py
spouk_utils/decorators.py
spouk_utils/utils.py
spouk_utils.egg-info/PKG-INFO
spouk_utils.egg-info/SOURCES.txt
spouk_utils.egg-info/dependency_links.txt
spouk_utils.egg-info/requires.txt
spouk_utils.egg-info/top_level.txt