Metadata-Version: 1.0
Name: spouk-utils
Version: 0.1
Summary: some utils for flask distributions
Home-page: UNKNOWN
Author: spouk
Author-email: spouk@spouk.ru
License: PSF
Keywords: spouk-utils,flask utils
Platform: UNKNOWN
